{
  "Boards": [
    {
      "id": 1,
      "name": "ASDFC8",
      "date": "10-11-2022",
      "description": "ASDXFC",
      "todo": [],
      "progress": [
        {
          "task": "hhhhh",
          "comments": [
            "fghj"
          ]
        },
        {
          "task": "jjjj",
          "comments": []
        },
        {
          "task": "llllllllll",
          "comments": []
        }
      ],
      "done": [
        {
          "task": "wdecfvew23ewdf",
          "comments": [
            "Love ",
            "Xmmm"
          ]
        },
        {
          "task": "hnjmk,l",
          "comments": []
        }
      ]
    }
  ]
}